<?xml version="1.0" encoding="UTF-8" standalone="no"?>
<partitionStats version="1.0">
<statistics>
  <statistic id="nExplicit" value="193"/>
  <statistic id="nData" value="68"/>
  <statistic id="nDyn" value="13"/>
  <statistic id="nDer" value="4"/>
  <statistic id="nAlgebraic" value="9"/>
  <statistic id="nBoundary" value="2"/>
  <statistic id="nEquations" value="206"/>
  <statistic id="nVariables" value="296"/>
  <statistic id="nNonLinearBoxes" value="7"/>
  <statistic id="nLinearBoxes" value="1"/>
  <statistic id="jacSizeFull" value="13"/>
  <statistic id="jacSize" value="13"/>
  <statistic id="jacSparseFactor" value="38"/>
</statistics>
</partitionStats>
